HISTORY.md
LICENSE
MANIFEST.in
README.md
npshmex.py
requirements.txt
setup.cfg
setup.py
npshmex.egg-info/PKG-INFO
npshmex.egg-info/SOURCES.txt
npshmex.egg-info/dependency_links.txt
npshmex.egg-info/not-zip-safe
npshmex.egg-info/requires.txt
npshmex.egg-info/top_level.txt
tests/test_npshmex.py