Metadata-Version: 2.1
Name: npshmex
Version: 0.2.1
Summary: ProcessPoolExecutor that passes numpyarrays through shared memory
Home-page: https://github.com/JelleAalbers/npshmex
Author: Jelle Aalbers
License: UNKNOWN
Platform: UNKNOWN
